{
  "components": {
    "pages": {
      "home": {
        "title": "Home",
        "return_button": "Return welcome page"
      },

      "notFound": {
        "title": "Page not found"
      },

      "settings": {
        "title": "Settings"
      },

      "welcome": {
        "title": "Template",

        "header": {
          "title": "Template",
          "navigation": "All services"
        },

        "hero": {
          "title": "Simple and powerful templates",
          "subTitle": "This template has all the features and design you need.",
          "button": "Get Started"
        },

        "features": [
          {
            "title": "Simple",
            "subTitle": "Very simple system and design"
          },

          {
            "title": "Powerful",
            "subTitle": "Well-designed code"
          },

          {
            "title": "Speedy",
            "subTitle": "Speed with Vite"
          }
        ]
      }
    }
  },

  "title": "Template"
}
